{
  "docwrightProfileVersion": "1",
  "name": "org-operations",
  "displayName": "Org Operations",
  "description": "Organizational operating system. Policy as the foundation of all work.",
  "principles": ["Security first", "Policy driven", "Test verified at every stage"],
  "proposalCategories": ["UI", "UX", "ENGINE", "DATA"],
  "effortSizes": { "XS": "~1d", "S": "~3d", "M": "~1w", "L": "~2w", "XL": "~1mo" },
  "version": "0.1.0",
  "documentTypes": ["inbox", "issue", "proposal", "plan", "policy", "decision", "work-item"],
  "states": {
    "policy":    ["draft", "active", "superseded", "archived"],
    "proposal":  ["inbox", "triaged", "evaluated", "accepted", "rejected"],
    "plan":      ["draft", "active", "completed", "canceled"],
    "issue":     ["inbox", "triaged", "resolved", "declined"],
    "decision":  ["draft", "final"],
    "work-item": ["backlog", "active", "done", "canceled"],
    "inbox":     ["new", "triaged"]
  },
  "requiredFrontmatter": ["type", "status", "created", "author", "author-role"],
  "optionalFrontmatter": ["parent", "policy-area", "tags", "origin", "ai-last-action",
    "category", "complexity", "estimated_effort", "depends_on", "due_date", "subsumed_by"],
  "sidebarExcludePatterns": ["AGENTS.md", "CHANGELOG.md", "CONTRIBUTING.md", "LICENSE", "NOTICE.md", "SECURITY.md", "PROPOSAL.md", "SESSION-LOG.md"],
  "hiddenDirectories": ["proposals/approved", "plans/completed"],
  "features": {
    "wikilinks": true,
    "graph": true,
    "naming": true,
    "llmWiki": false
  }
}
